CHANGELOG.rst
MANIFEST.in
README.rst
default.nix
pip2nix.ini
pip2nix.release.ini
python-packages.nix
release-python-packages.nix
release-shell.nix
release.nix
setup.cfg
setup.py
docs/HACKING.rst
docs/changelog.rst
docs/conf.py
docs/configuration.rst
docs/examples.rst
docs/getting_started.rst
docs/index.rst
docs/tips.rst
pip2nix/__init__.py
pip2nix/cli.py
pip2nix/config.py
pip2nix/confspec.ini
pip2nix/default.nix.j2
pip2nix/egg_writer.py
pip2nix/generate.py
pip2nix/main.py
pip2nix/python-packages-overrides.nix.j2
pip2nix.egg-info/PKG-INFO
pip2nix.egg-info/SOURCES.txt
pip2nix.egg-info/dependency_links.txt
pip2nix.egg-info/entry_points.txt
pip2nix.egg-info/requires.txt
pip2nix.egg-info/tests_require.txt
pip2nix.egg-info/top_level.txt
pip2nix/models/__init__.py
pip2nix/models/package.py
pip2nix/models/requirement_set.py