Metadata-Version: 1.1
Name: pip2nix
Version: 0.7.0
Summary: Generate Nix expressions for Python packages.
Home-page: https://github.com/johbo/pip2nix
Author: Tomasz Kontusz
Author-email: tomasz.kontusz@gmail.com
License: GPLv3+
Keywords: nix pip
Platform: UNKNOWN
Classifier: Development Status :: 4 - Beta
Classifier: Intended Audience :: Developers
Classifier: Topic :: Software Development :: Build Tools
Classifier: License :: OSI Approved :: GNU General Public License v3 or later (GPLv3+)
Classifier: Programming Language :: Python :: 2
Classifier: Programming Language :: Python :: 2.7
Classifier: Programming Language :: Python :: 3
Classifier: Programming Language :: Python :: 3.3
Classifier: Programming Language :: Python :: 3.4
Classifier: Programming Language :: Python :: 3.5
Classifier: Programming Language :: Python :: 3.6
